pycaw/__init__.py
pycaw/cmc.py
pycaw/defillama/__init__.py
pycaw/defillama/defillama.py
pycaw/defillama/helpers.py
pycaw/eth.py
pycaw/etherscan/__init__.py
pycaw/etherscan/decoding_utils.py
pycaw/etherscan/etherscan_connector.py
pycaw/etherscan/types.py
pycaw/ftmscan.py
pycaw/messari/LICENSE
pycaw/messari/__init__.py
pycaw/messari/dataloader.py
pycaw/messari/examples/README.md
pycaw/messari/examples/requirement.txt
pycaw/messari/examples/tvl_monitor.py
pycaw/messari/helpers.py
pycaw/messari/mappings/messari_to_dl.json
pycaw/messari/mappings/messari_to_dl_hardcode.json
pycaw/messari/messari_api.py
pycaw/messari/requirements.txt
pycaw/messari/utils.py
pycaw/messari_api.py
python_caw-0.0.3.dist-info/LICENSE
python_caw-0.0.3.dist-info/WHEEL
python_caw-0.0.3.dist-info/METADATA
python_caw-0.0.3.dist-info/RECORD
