Metadata-Version: 2.1
Name: python-caw
Version: 0.0.3
Summary: A Python package for wrapping common Crypto APIs like Etherscan, Messari, CoinGecko, and Coin Market Cap
License: MIT
Author: Unique-Divine
Author-email: realuniquedivine@gmail.com
Requires-Python: >=3.9,<4.0
Classifier: License :: OSI Approved :: MIT License
Classifier: Programming Language :: Python :: 3
Classifier: Programming Language :: Python :: 3.10
Classifier: Programming Language :: Python :: 3.9
Requires-Dist: eth-utils (==1.9.5)
Requires-Dist: pandas (>=1.4.3,<2.0.0)
Requires-Dist: python-dotenv (>=0.20.0,<0.21.0)
Requires-Dist: requests (>=2.28.1,<3.0.0)
Requires-Dist: web3 (>=5.30.0,<6.0.0)
